{"posts_test.md":"QX2b88Wr","posts_git_error443.md":"3HPnqwZT","posts_vitepress_vitepress.md":"Q2o0NiDy","posts_vitepress_侧边栏.md":"0Yf88gBc","index.md":"BqFWf5pZ","study_python.md":"4pEAmfA3","guide_index.md":"QXmr9Qxd","study_前端.md":"NsHDySmD","posts_vitepress_主页.md":"hsnP3dPu","posts_vitepress_导航栏.md":"jYiPY1VW","posts_阅读须知.md":"Cn_LdntF","guide_test.md":"R7g-OfdW","posts_vitepress_介绍.md":"aKCaBB7B","study_c__.md":"02tj2vys","study_数据结构.md":"bcfASdWK","posts_vitepress_快速上手.md":"ZcEtMOPH","study_学习笔记.md":"2XoBRyTv"}
